{"schemaVersion":{"major":0,"minor":3,"patch":0},"primaryContentSections":[{"kind":"declarations","declarations":[{"languages":["swift"],"platforms":["macOS"],"tokens":[{"kind":"keyword","text":"init"},{"kind":"text","text":"("},{"text":"uri","kind":"externalParam"},{"text":": ","kind":"text"},{"kind":"typeIdentifier","preciseIdentifier":"s:10ATProtoKit13ATProtocolURIV","text":"ATProtocolURI","identifier":"doc:\/\/ATProtoKit\/documentation\/ATProtoKit\/ATProtocolURI"},{"kind":"text","text":", "},{"kind":"externalParam","text":"cid"},{"kind":"text","text":": "},{"kind":"typeIdentifier","text":"String","preciseIdentifier":"s:SS"},{"kind":"text","text":", "},{"text":"value","kind":"externalParam"},{"text":": ","kind":"text"},{"preciseIdentifier":"s:10ATProtoKit9JSONValueO","text":"JSONValue","kind":"typeIdentifier","identifier":"doc:\/\/ATProtoKit\/documentation\/ATProtoKit\/JSONValue"},{"kind":"text","text":", "},{"text":"blobs","kind":"externalParam"},{"text":": [","kind":"text"},{"text":"ComAtprotoAdminDefs","identifier":"doc:\/\/ATProtoKit\/documentation\/ATProtoKit\/ComAtprotoAdminDefs","kind":"typeIdentifier","preciseIdentifier":"s:10ATProtoKit19ComAtprotoAdminDefsV"},{"text":".","kind":"text"},{"kind":"typeIdentifier","text":"BlobView","preciseIdentifier":"s:10ATProtoKit19ComAtprotoAdminDefsV8BlobViewV","identifier":"doc:\/\/ATProtoKit\/documentation\/ATProtoKit\/ComAtprotoAdminDefs\/BlobView"},{"kind":"text","text":"], "},{"kind":"externalParam","text":"labels"},{"kind":"text","text":": ["},{"text":"ComAtprotoLabelDefs","preciseIdentifier":"s:10ATProtoKit19ComAtprotoLabelDefsV","kind":"typeIdentifier","identifier":"doc:\/\/ATProtoKit\/documentation\/ATProtoKit\/ComAtprotoLabelDefs"},{"text":".","kind":"text"},{"kind":"typeIdentifier","identifier":"doc:\/\/ATProtoKit\/documentation\/ATProtoKit\/ComAtprotoLabelDefs\/Label","preciseIdentifier":"s:10ATProtoKit19ComAtprotoLabelDefsV0E0V","text":"Label"},{"kind":"text","text":"]?, "},{"text":"indexedAt","kind":"externalParam"},{"text":": ","kind":"text"},{"text":"ATProtocolDate","kind":"typeIdentifier","preciseIdentifier":"s:10ATProtoKit14ATProtocolDateV","identifier":"doc:\/\/ATProtoKit\/documentation\/ATProtoKit\/ATProtocolDate"},{"kind":"text","text":", "},{"text":"moderation","kind":"externalParam"},{"kind":"text","text":": "},{"text":"ComAtprotoAdminDefs","preciseIdentifier":"s:10ATProtoKit19ComAtprotoAdminDefsV","identifier":"doc:\/\/ATProtoKit\/documentation\/ATProtoKit\/ComAtprotoAdminDefs","kind":"typeIdentifier"},{"kind":"text","text":"."},{"kind":"typeIdentifier","preciseIdentifier":"s:10ATProtoKit19ComAtprotoAdminDefsV16ModerationDetailV","text":"ModerationDetail","identifier":"doc:\/\/ATProtoKit\/documentation\/ATProtoKit\/ComAtprotoAdminDefs\/ModerationDetail"},{"text":", ","kind":"text"},{"text":"repo","kind":"externalParam"},{"text":": ","kind":"text"},{"preciseIdentifier":"s:10ATProtoKit19ComAtprotoAdminDefsV","text":"ComAtprotoAdminDefs","identifier":"doc:\/\/ATProtoKit\/documentation\/ATProtoKit\/ComAtprotoAdminDefs","kind":"typeIdentifier"},{"kind":"text","text":"."},{"preciseIdentifier":"s:10ATProtoKit19ComAtprotoAdminDefsV8RepoViewV","identifier":"doc:\/\/ATProtoKit\/documentation\/ATProtoKit\/ComAtprotoAdminDefs\/RepoView","text":"RepoView","kind":"typeIdentifier"},{"kind":"text","text":")"}]}]}],"kind":"symbol","variants":[{"paths":["\/documentation\/atprotokit\/comatprotoadmindefs\/recordviewdetail\/init(uri:cid:value:blobs:labels:indexedat:moderation:repo:)"],"traits":[{"interfaceLanguage":"swift"}]}],"metadata":{"symbolKind":"init","modules":[{"name":"ATProtoKit"}],"fragments":[{"kind":"identifier","text":"init"},{"kind":"text","text":"("},{"text":"uri","kind":"externalParam"},{"kind":"text","text":": "},{"preciseIdentifier":"s:10ATProtoKit13ATProtocolURIV","text":"ATProtocolURI","kind":"typeIdentifier"},{"text":", ","kind":"text"},{"kind":"externalParam","text":"cid"},{"text":": ","kind":"text"},{"preciseIdentifier":"s:SS","kind":"typeIdentifier","text":"String"},{"text":", ","kind":"text"},{"text":"value","kind":"externalParam"},{"kind":"text","text":": "},{"preciseIdentifier":"s:10ATProtoKit9JSONValueO","text":"JSONValue","kind":"typeIdentifier"},{"kind":"text","text":", "},{"kind":"externalParam","text":"blobs"},{"kind":"text","text":": ["},{"text":"ComAtprotoAdminDefs","kind":"typeIdentifier","preciseIdentifier":"s:10ATProtoKit19ComAtprotoAdminDefsV"},{"text":".","kind":"text"},{"text":"BlobView","preciseIdentifier":"s:10ATProtoKit19ComAtprotoAdminDefsV8BlobViewV","kind":"typeIdentifier"},{"kind":"text","text":"], "},{"kind":"externalParam","text":"labels"},{"text":": [","kind":"text"},{"kind":"typeIdentifier","text":"ComAtprotoLabelDefs","preciseIdentifier":"s:10ATProtoKit19ComAtprotoLabelDefsV"},{"text":".","kind":"text"},{"kind":"typeIdentifier","text":"Label","preciseIdentifier":"s:10ATProtoKit19ComAtprotoLabelDefsV0E0V"},{"kind":"text","text":"]?, "},{"kind":"externalParam","text":"indexedAt"},{"kind":"text","text":": "},{"kind":"typeIdentifier","preciseIdentifier":"s:10ATProtoKit14ATProtocolDateV","text":"ATProtocolDate"},{"kind":"text","text":", "},{"text":"moderation","kind":"externalParam"},{"text":": ","kind":"text"},{"kind":"typeIdentifier","preciseIdentifier":"s:10ATProtoKit19ComAtprotoAdminDefsV","text":"ComAtprotoAdminDefs"},{"text":".","kind":"text"},{"text":"ModerationDetail","kind":"typeIdentifier","preciseIdentifier":"s:10ATProtoKit19ComAtprotoAdminDefsV16ModerationDetailV"},{"kind":"text","text":", "},{"text":"repo","kind":"externalParam"},{"kind":"text","text":": "},{"preciseIdentifier":"s:10ATProtoKit19ComAtprotoAdminDefsV","text":"ComAtprotoAdminDefs","kind":"typeIdentifier"},{"text":".","kind":"text"},{"text":"RepoView","kind":"typeIdentifier","preciseIdentifier":"s:10ATProtoKit19ComAtprotoAdminDefsV8RepoViewV"},{"text":")","kind":"text"}],"externalID":"s:10ATProtoKit19ComAtprotoAdminDefsV16RecordViewDetailV3uri3cid5value5blobs6labels9indexedAt10moderation4repoAeA13ATProtocolURIV_SSAA9JSONValueOSayAC04BlobH0VGSayAA0cd5LabelF0V0W0VGSgAA0S4DateVAC010ModerationI0VAC04RepoH0Vtcfc","roleHeading":"Initializer","title":"init(uri:cid:value:blobs:labels:indexedAt:moderation:repo:)","role":"symbol"},"identifier":{"url":"doc:\/\/ATProtoKit\/documentation\/ATProtoKit\/ComAtprotoAdminDefs\/RecordViewDetail\/init(uri:cid:value:blobs:labels:indexedAt:moderation:repo:)","interfaceLanguage":"swift"},"hierarchy":{"paths":[["doc:\/\/ATProtoKit\/documentation\/ATProtoKit","doc:\/\/ATProtoKit\/documentation\/ATProtoKit\/ComAtprotoAdminDefs","doc:\/\/ATProtoKit\/documentation\/ATProtoKit\/ComAtprotoAdminDefs\/RecordViewDetail"]]},"sections":[],"references":{"doc://ATProtoKit/documentation/ATProtoKit/ComAtprotoAdminDefs/ModerationDetail":{"role":"symbol","abstract":[],"kind":"symbol","url":"\/documentation\/atprotokit\/comatprotoadmindefs\/moderationdetail","fragments":[{"text":"struct","kind":"keyword"},{"kind":"text","text":" "},{"kind":"identifier","text":"ModerationDetail"}],"type":"topic","title":"ComAtprotoAdminDefs.ModerationDetail","navigatorTitle":[{"kind":"identifier","text":"ModerationDetail"}],"identifier":"doc:\/\/ATProtoKit\/documentation\/ATProtoKit\/ComAtprotoAdminDefs\/ModerationDetail"},"doc://ATProtoKit/documentation/ATProtoKit/ComAtprotoAdminDefs":{"identifier":"doc:\/\/ATProtoKit\/documentation\/ATProtoKit\/ComAtprotoAdminDefs","title":"ComAtprotoAdminDefs","type":"topic","role":"symbol","fragments":[{"text":"struct","kind":"keyword"},{"kind":"text","text":" "},{"text":"ComAtprotoAdminDefs","kind":"identifier"}],"navigatorTitle":[{"text":"ComAtprotoAdminDefs","kind":"identifier"}],"abstract":[],"kind":"symbol","url":"\/documentation\/atprotokit\/comatprotoadmindefs"},"doc://ATProtoKit/documentation/ATProtoKit/ATProtocolDate":{"role":"symbol","fragments":[{"kind":"keyword","text":"struct"},{"kind":"text","text":" "},{"text":"ATProtocolDate","kind":"identifier"}],"type":"topic","title":"ATProtocolDate","url":"\/documentation\/atprotokit\/atprotocoldate","kind":"symbol","navigatorTitle":[{"kind":"identifier","text":"ATProtocolDate"}],"identifier":"doc:\/\/ATProtoKit\/documentation\/ATProtoKit\/ATProtocolDate","abstract":[]},"doc://ATProtoKit/documentation/ATProtoKit":{"role":"collection","type":"topic","title":"ATProtoKit","url":"\/documentation\/atprotokit","identifier":"doc:\/\/ATProtoKit\/documentation\/ATProtoKit","abstract":[],"kind":"symbol"},"doc://ATProtoKit/documentation/ATProtoKit/ATProtocolURI":{"type":"topic","title":"ATProtocolURI","abstract":[],"fragments":[{"kind":"keyword","text":"struct"},{"text":" ","kind":"text"},{"text":"ATProtocolURI","kind":"identifier"}],"identifier":"doc:\/\/ATProtoKit\/documentation\/ATProtoKit\/ATProtocolURI","kind":"symbol","role":"symbol","navigatorTitle":[{"text":"ATProtocolURI","kind":"identifier"}],"url":"\/documentation\/atprotokit\/atprotocoluri"},"doc://ATProtoKit/documentation/ATProtoKit/ComAtprotoLabelDefs":{"identifier":"doc:\/\/ATProtoKit\/documentation\/ATProtoKit\/ComAtprotoLabelDefs","title":"ComAtprotoLabelDefs","role":"symbol","url":"\/documentation\/atprotokit\/comatprotolabeldefs","abstract":[],"fragments":[{"text":"struct","kind":"keyword"},{"text":" ","kind":"text"},{"kind":"identifier","text":"ComAtprotoLabelDefs"}],"navigatorTitle":[{"text":"ComAtprotoLabelDefs","kind":"identifier"}],"type":"topic","kind":"symbol"},"doc://ATProtoKit/documentation/ATProtoKit/ComAtprotoAdminDefs/RepoView":{"role":"symbol","identifier":"doc:\/\/ATProtoKit\/documentation\/ATProtoKit\/ComAtprotoAdminDefs\/RepoView","kind":"symbol","type":"topic","navigatorTitle":[{"kind":"identifier","text":"RepoView"}],"url":"\/documentation\/atprotokit\/comatprotoadmindefs\/repoview","title":"ComAtprotoAdminDefs.RepoView","abstract":[],"fragments":[{"kind":"keyword","text":"struct"},{"text":" ","kind":"text"},{"kind":"identifier","text":"RepoView"}]},"doc://ATProtoKit/documentation/ATProtoKit/ComAtprotoAdminDefs/BlobView":{"abstract":[],"fragments":[{"text":"struct","kind":"keyword"},{"kind":"text","text":" "},{"kind":"identifier","text":"BlobView"}],"type":"topic","navigatorTitle":[{"kind":"identifier","text":"BlobView"}],"url":"\/documentation\/atprotokit\/comatprotoadmindefs\/blobview","kind":"symbol","identifier":"doc:\/\/ATProtoKit\/documentation\/ATProtoKit\/ComAtprotoAdminDefs\/BlobView","role":"symbol","title":"ComAtprotoAdminDefs.BlobView"},"doc://ATProtoKit/documentation/ATProtoKit/ComAtprotoAdminDefs/RecordViewDetail/init(uri:cid:value:blobs:labels:indexedAt:moderation:repo:)":{"abstract":[],"type":"topic","title":"init(uri:cid:value:blobs:labels:indexedAt:moderation:repo:)","identifier":"doc:\/\/ATProtoKit\/documentation\/ATProtoKit\/ComAtprotoAdminDefs\/RecordViewDetail\/init(uri:cid:value:blobs:labels:indexedAt:moderation:repo:)","url":"\/documentation\/atprotokit\/comatprotoadmindefs\/recordviewdetail\/init(uri:cid:value:blobs:labels:indexedat:moderation:repo:)","fragments":[{"text":"init","kind":"identifier"},{"kind":"text","text":"("},{"kind":"externalParam","text":"uri"},{"text":": ","kind":"text"},{"preciseIdentifier":"s:10ATProtoKit13ATProtocolURIV","text":"ATProtocolURI","kind":"typeIdentifier"},{"kind":"text","text":", "},{"kind":"externalParam","text":"cid"},{"text":": ","kind":"text"},{"text":"String","preciseIdentifier":"s:SS","kind":"typeIdentifier"},{"text":", ","kind":"text"},{"text":"value","kind":"externalParam"},{"text":": ","kind":"text"},{"kind":"typeIdentifier","text":"JSONValue","preciseIdentifier":"s:10ATProtoKit9JSONValueO"},{"text":", ","kind":"text"},{"text":"blobs","kind":"externalParam"},{"kind":"text","text":": ["},{"kind":"typeIdentifier","preciseIdentifier":"s:10ATProtoKit19ComAtprotoAdminDefsV","text":"ComAtprotoAdminDefs"},{"text":".","kind":"text"},{"kind":"typeIdentifier","preciseIdentifier":"s:10ATProtoKit19ComAtprotoAdminDefsV8BlobViewV","text":"BlobView"},{"kind":"text","text":"], "},{"text":"labels","kind":"externalParam"},{"text":": [","kind":"text"},{"text":"ComAtprotoLabelDefs","kind":"typeIdentifier","preciseIdentifier":"s:10ATProtoKit19ComAtprotoLabelDefsV"},{"text":".","kind":"text"},{"text":"Label","kind":"typeIdentifier","preciseIdentifier":"s:10ATProtoKit19ComAtprotoLabelDefsV0E0V"},{"text":"]?, ","kind":"text"},{"kind":"externalParam","text":"indexedAt"},{"kind":"text","text":": "},{"preciseIdentifier":"s:10ATProtoKit14ATProtocolDateV","text":"ATProtocolDate","kind":"typeIdentifier"},{"text":", ","kind":"text"},{"text":"moderation","kind":"externalParam"},{"kind":"text","text":": "},{"preciseIdentifier":"s:10ATProtoKit19ComAtprotoAdminDefsV","kind":"typeIdentifier","text":"ComAtprotoAdminDefs"},{"text":".","kind":"text"},{"kind":"typeIdentifier","text":"ModerationDetail","preciseIdentifier":"s:10ATProtoKit19ComAtprotoAdminDefsV16ModerationDetailV"},{"text":", ","kind":"text"},{"text":"repo","kind":"externalParam"},{"kind":"text","text":": "},{"kind":"typeIdentifier","text":"ComAtprotoAdminDefs","preciseIdentifier":"s:10ATProtoKit19ComAtprotoAdminDefsV"},{"text":".","kind":"text"},{"preciseIdentifier":"s:10ATProtoKit19ComAtprotoAdminDefsV8RepoViewV","text":"RepoView","kind":"typeIdentifier"},{"text":")","kind":"text"}],"kind":"symbol","role":"symbol"},"doc://ATProtoKit/documentation/ATProtoKit/ComAtprotoAdminDefs/RecordViewDetail":{"abstract":[],"type":"topic","role":"symbol","identifier":"doc:\/\/ATProtoKit\/documentation\/ATProtoKit\/ComAtprotoAdminDefs\/RecordViewDetail","fragments":[{"text":"struct","kind":"keyword"},{"text":" ","kind":"text"},{"text":"RecordViewDetail","kind":"identifier"}],"navigatorTitle":[{"text":"RecordViewDetail","kind":"identifier"}],"kind":"symbol","title":"ComAtprotoAdminDefs.RecordViewDetail","url":"\/documentation\/atprotokit\/comatprotoadmindefs\/recordviewdetail"},"doc://ATProtoKit/documentation/ATProtoKit/JSONValue":{"title":"JSONValue","identifier":"doc:\/\/ATProtoKit\/documentation\/ATProtoKit\/JSONValue","type":"topic","role":"symbol","fragments":[{"text":"enum","kind":"keyword"},{"text":" ","kind":"text"},{"text":"JSONValue","kind":"identifier"}],"navigatorTitle":[{"text":"JSONValue","kind":"identifier"}],"abstract":[],"kind":"symbol","url":"\/documentation\/atprotokit\/jsonvalue"},"doc://ATProtoKit/documentation/ATProtoKit/ComAtprotoLabelDefs/Label":{"abstract":[],"type":"topic","title":"ComAtprotoLabelDefs.Label","navigatorTitle":[{"kind":"identifier","text":"Label"}],"identifier":"doc:\/\/ATProtoKit\/documentation\/ATProtoKit\/ComAtprotoLabelDefs\/Label","fragments":[{"text":"struct","kind":"keyword"},{"kind":"text","text":" "},{"text":"Label","kind":"identifier"}],"kind":"symbol","role":"symbol","url":"\/documentation\/atprotokit\/comatprotolabeldefs\/label"}}}